bot/__init__.py
bot/callbacks.py
bot/config.py
bot/helptexts.py
bot/utilsbot.py
bot/sql/__init__.py
bot/sql/antifloodsql.py
bot/sql/blacklistsql.py
bot/sql/filtersql.py
bot/sql/goodbyesql.py
bot/sql/notessql.py
bot/sql/rulessql.py
bot/sql/urlblacklistsql.py
bot/sql/warnsql.py
bot/sql/welcomesql.py
utilsrobot-3.5.dist-info/LICENSE
utilsrobot-3.5.dist-info/METADATA
utilsrobot-3.5.dist-info/WHEEL
utilsrobot-3.5.dist-info/top_level.txt
utilsrobot-3.5.dist-info/RECORD
