Metadata-Version: 2.1
Name: utilsrobot
Version: 3.5
Summary: A Powerful Python-Telethon Based Library For Spidy's Bots.
Home-page: https://github.com/sppidy
Author: sppidy
Author-email: sppidytg@gmail.com
License: GNU AFFERO GENERAL PUBLIC LICENSE (v3)
Platform: UNKNOWN
Classifier: Programming Language :: Python :: 3
Classifier: License :: OSI Approved :: GNU General Public License v3 (GPLv3)
Classifier: Operating System :: OS Independent
Requires-Python: >=3.6
Requires-Dist: SQLAlchemy (==1.3.0)
Requires-Dist: cryptg
Requires-Dist: python-dotenv (==0.15.0)
Requires-Dist: redshift-sqlalchemy
Requires-Dist: telethon (==1.19.5)
